{"sports":[{"id":"600","uid":"s:600","guid":"119cfa41-71d4-39bf-a790-6273a52b0259","name":"Soccer","slug":"soccer","logos":[{"href":"https://a.espncdn.com/combiner/i?img=/guid/119cfa41-71d4-39bf-a790-6273a52b0259/logos/default.png","alt":"","rel":["full","default"],"width":500,"height":500},{"href":"https://a.espncdn.com/combiner/i?img=/guid/119cfa41-71d4-39bf-a790-6273a52b0259/logos/default-dark.png","alt":"","rel":["full","dark"],"width":500,"height":500}],"leagues":[{"id":"700","uid":"s:600~l:700","name":"English Premier League","abbreviation":"Premier League","shortName":"English Premier League","slug":"eng.1","tag":"eng.1","isTournament":false,"smartdates":["2025-11-08T08:00Z","2025-11-09T08:00Z","2025-11-22T08:00Z"],"events":[{"id":"740697","uid":"s:600~l:700~e:740697~c:740697","guid":"7d95eb8b-d855-368d-80e5-7fa2da8b13b6","date":"2025-11-09T14:00:00Z","timeValid":true,"recent":false,"name":"2025-26 English Premier League","shortName":"2025-26 English Premier League","links":[{"rel":["summary","desktop","event"],"href":"https://www.espn.com/soccer/match/_/gameId/740697/afc-bournemouth-aston-villa","text":"Summary"},{"rel":["recap","desktop","event"],"href":"https://www.espn.com/soccer/report/_/gameId/740697","text":"Report"},{"rel":["stats","desktop","event"],"href":"https://www.espn.com/soccer/matchstats/_/gameId/740697","text":"Statistics"}],"gamecastAvailable":true,"playByPlayAvailable":true,"commentaryAvailable":true,"wallclockAvailable":true,"fauxcastAvailable":false,"onWatch":false,"competitionId":"740697","location":"Villa Park","season":2025,"seasonStartDate":"2025-06-01T04:00:00Z","seasonEndDate":"2026-06-01T03:59:00Z","seasonType":"1","seasonTypeHasGroups":false,"group":{"groupId":"1","name":"2025-26 English Premier League","abbreviation":"2025-26 English Premier League","shortName":"2025-26 English Premier League"},"link":"https://www.espn.com/soccer/match/_/gameId/740697/afc-bournemouth-aston-villa","status":"post","summary":"FT","period":2,"clock":"90'+4'","addedClock":240.0,"broadcasts":[{"typeId":1,"type":"TV","isNational":true,"broadcasterId":519,"broadcastId":519,"name":"USA Network","shortName":"USA Net","callLetters":"USA Net","lang":"en","region":"us","slug":""}],"broadcast":"USA Net","odds":{"details":"AVL +125","overUnder":2.5,"spread":-0.5,"overOdds":-125,"underOdds":-105,"provider":{"id":"58","name":"ESPN BET","priority":1,"logos":[{"href":"https://a.espncdn.com/i/espnbet/ESPN_Bet_Sportsbook_Light.svg","rel":["light"]},{"href":"https://a.espncdn.com/i/espnbet/ESPN_Bet_Sportsbook_Dark.svg","rel":["dark"]}]},"home":{"moneyLine":125},"away":{"moneyLine":200},"draw":{"moneyLine":260},"awayTeamOdds":{"favorite":false,"favoriteAtOpen":true,"underdog":true,"moneyLine":200,"spreadOdds":-160,"team":{"id":"349","abbreviation":"BOU","displayName":"AFC Bournemouth","name":"Bournemouth"}},"homeTeamOdds":{"favorite":true,"favoriteAtOpen":false,"underdog":false,"moneyLine":125,"spreadOdds":115,"team":{"id":"362","abbreviation":"AVL","displayName":"Aston Villa","name":"Aston Villa"}},"drawOdds":{"moneyLine":260},"links":[{"language":"en-US","rel":["game","desktop","bets"],"href":"https://espnbet.app.link/integrations?%243p=a_espn&clr=espnbettingintegration&$canonical_url=/sport/soccer/organization/england/competition/premier-league/event/3be451af-6b07-4eb8-b9ca-0ef02317e2a2","text":"Game","shortText":"Game","isExternal":true,"isPremium":false}],"pointSpread":{"displayName":"Spread","shortDisplayName":"Spread","home":{"open":{"line":"+0.5","odds":"-350"},"close":{"line":"-0.5","odds":"+115","outcome":"WIN","icon":"https://a.espncdn.com/i/espnbet/espn-bet-checkmark-bold.png","iconDark":"https://a.espncdn.com/i/espnbet/dark/espn-bet-checkmark-bold.png"},"current":{"line":"-4.5","odds":"+400"}},"away":{"open":{"line":"-0.5","odds":"+230"},"close":{"line":"+0.5","odds":"-160","outcome":"LOSS"},"current":{"line":"+4.5","odds":"-1200"}}},"moneyline":{"displayName":"Moneyline","shortDisplayName":"ML","home":{"open":{"odds":"EVEN"},"close":{"odds":"+125","outcome":"WIN","icon":"https://a.espncdn.com/i/espnbet/espn-bet-checkmark-bold.png","iconDark":"https://a.espncdn.com/i/espnbet/dark/espn-bet-checkmark-bold.png"},"current":{"odds":"-20000"}},"away":{"open":{"odds":"+255"},"close":{"odds":"+200","outcome":"LOSS"},"current":{"odds":"+8000"}},"draw":{"open":{"odds":"+250"},"close":{"odds":"+260","outcome":"LOSS"},"current":{"odds":"+1700"}}},"total":{"displayName":"Total","shortDisplayName":"Total","over":{"open":{"line":"o0.5","odds":"-2000"},"close":{"line":"o2.5","odds":"-125","outcome":"WIN","icon":"https://a.espncdn.com/i/espnbet/espn-bet-checkmark-bold.png","iconDark":"https://a.espncdn.com/i/espnbet/dark/espn-bet-checkmark-bold.png"},"current":{"line":"o4.5","odds":"+1100"}},"under":{"open":{"line":"u0.5","odds":"+850"},"close":{"line":"u2.5","odds":"-105","outcome":"LOSS"},"current":{"line":"u4.5","odds":"-5000"}}},"header":{"logo":{"light":"https://a.espncdn.com/i/espnbet/espn-bet-square-off.svg","dark":"https://a.espncdn.com/i/espnbet/dark/espn-bet-square-off.svg","exclusivesLogoDark":"https://a.espncdn.com/i/espnbet/espn-bet-square-mint.svg","exclusivesLogoLight":"https://a.espncdn.com/i/espnbet/espn-bet-square-mint.svg"},"text":"ESPN Bet Sportsbook"}},"fullStatus":{"clock":5400.0,"addedClock":240.0,"displayClock":"90'+4'","period":2,"displayPeriod":"2nd","type":{"id":"28","name":"STATUS_FULL_TIME","state":"post","completed":true,"description":"Full Time","detail":"FT","shortDetail":"FT"}},"competitors":[{"id":"349","guid":"1e76c2fe-68a5-3950-8881-47e916c0c115","uid":"s:600~t:349","type":"team","order":1,"homeAway":"away","winner":false,"form":"LLWDW","displayName":"AFC Bournemouth","name":"Bournemouth","abbreviation":"BOU","location":"AFC Bournemouth","color":"f42727","alternateColor":"ffffff","score":"0","isNational":false,"links":[{"language":"en-US","rel":["clubhouse","desktop","team"],"href":"https://www.espn.com/soccer/club/_/id/349/afc-bournemouth","text":"Clubhouse","shortText":"Clubhouse","isExternal":false,"isPremium":false,"isHidden":false},{"language":"en-US","rel":["stats","desktop","team"],"href":"https://www.espn.com/soccer/team/stats/_/id/349/afc-bournemouth","text":"Stats","shortText":"Stats","isExternal":false,"isPremium":false,"isHidden":false},{"language":"en-US","rel":["schedule","desktop","team"],"href":"https://www.espn.com/soccer/team/fixtures/_/id/349/afc-bournemouth","text":"Fixtures","shortText":"Fixtures","isExternal":false,"isPremium":false,"isHidden":false},{"language":"en-US","rel":["results","desktop","team"],"href":"https://www.espn.com/soccer/team/results/_/id/349/afc-bournemouth","text":"Results","shortText":"Results","isExternal":false,"isPremium":false,"isHidden":false},{"language":"en-US","rel":["standings","desktop","team"],"href":"https://www.espn.com/soccer/standings/_/league/eng.1","text":"Standings","shortText":"Standings","isExternal":false,"isPremium":false,"isHidden":false},{"language":"en-US","rel":["squad","desktop","team"],"href":"https://www.espn.com/soccer/team/squad/_/id/349/afc-bournemouth","text":"Squad","shortText":"Squad","isExternal":false,"isPremium":false,"isHidden":false}],"record":"5-3-3, 18 pts","records":[],"group":"1","recordStats":{"awayPointsFor":{"value":9.0},"pointsAgainst":{"value":18.0},"awayGamesPlayed":{"value":6.0},"awayWins":{"value":1.0},"losses":{"value":3.0},"points":{"value":18.0},"homeWins":{"value":4.0},"pointDifferential":{"value":-1.0},"homePointsAgainst":{"value":2.0},"gamesPlayed":{"value":11.0},"ties":{"value":3.0},"awayLosses":{"value":3.0},"rank":{"value":9.0},"homePointsFor":{"value":8.0},"awayTies":{"value":2.0},"wins":{"value":5.0},"homeTies":{"value":1.0},"pointsFor":{"value":17.0},"homeLosses":{"value":0.0},"streak":{"value":0.0},"homeGamesPlayed":{"value":5.0},"awayPointsAgainst":{"value":16.0}},"logo":"https://a.espncdn.com/i/teamlogos/soccer/500/349.png","logoDark":"https://a.espncdn.com/i/teamlogos/soccer/500-dark/349.png","goalieSummary":[{"displayValue":"4 GA, 4 SV","athlete":{"id":"289824","displayName":"Djordje Petrovic","shortName":"D Petrovic","fullName":"Djordje Petrovic","lastName":"Petrovic","jersey":"1","team":{"id":"349"},"position":"G"}}]},{"id":"362","guid":"610557ff-e870-ea0e-a3b2-8244df325d22","uid":"s:600~t:362","type":"team","order":0,"homeAway":"home","winner":true,"form":"WWLWL","displayName":"Aston Villa","name":"Aston Villa","abbreviation":"AVL","location":"Aston Villa","color":"660e36","alternateColor":"ffffff","score":"4","isNational":false,"links":[{"language":"en-US","rel":["clubhouse","desktop","team"],"href":"https://www.espn.com/soccer/club/_/id/362/aston-villa","text":"Clubhouse","shortText":"Clubhouse","isExternal":false,"isPremium":false,"isHidden":false},{"language":"en-US","rel":["stats","desktop","team"],"href":"https://www.espn.com/soccer/team/stats/_/id/362/aston-villa","text":"Stats","shortText":"Stats","isExternal":false,"isPremium":false,"isHidden":false},{"language":"en-US","rel":["schedule","desktop","team"],"href":"https://www.espn.com/soccer/team/fixtures/_/id/362/aston-villa","text":"Fixtures","shortText":"Fixtures","isExternal":false,"isPremium":false,"isHidden":false},{"language":"en-US","rel":["results","desktop","team"],"href":"https://www.espn.com/soccer/team/results/_/id/362/aston-villa","text":"Results","shortText":"Results","isExternal":false,"isPremium":false,"isHidden":false},{"language":"en-US","rel":["standings","desktop","team"],"href":"https://www.espn.com/soccer/standings/_/league/eng.1","text":"Standings","shortText":"Standings","isExternal":false,"isPremium":false,"isHidden":false},{"language":"en-US","rel":["squad","desktop","team"],"href":"https://www.espn.com/soccer/team/squad/_/id/362/aston-villa","text":"Squad","shortText":"Squad","isExternal":false,"isPremium":false,"isHidden":false}],"record":"5-3-3, 18 pts","records":[],"group":"1","recordStats":{"awayPointsFor":{"value":3.0},"pointsAgainst":{"value":10.0},"awayGamesPlayed":{"value":5.0},"awayWins":{"value":1.0},"losses":{"value":3.0},"points":{"value":18.0},"homeWins":{"value":4.0},"pointDifferential":{"value":3.0},"homePointsAgainst":{"value":5.0},"gamesPlayed":{"value":11.0},"ties":{"value":3.0},"awayLosses":{"value":2.0},"rank":{"value":6.0},"homePointsFor":{"value":10.0},"awayTies":{"value":2.0},"wins":{"value":5.0},"homeTies":{"value":1.0},"pointsFor":{"value":13.0},"homeLosses":{"value":1.0},"streak":{"value":0.0},"homeGamesPlayed":{"value":6.0},"awayPointsAgainst":{"value":5.0}},"logo":"https://a.espncdn.com/i/teamlogos/soccer/500/362.png","logoDark":"https://a.espncdn.com/i/teamlogos/soccer/500-dark/362.png","goalieSummary":[{"displayValue":"0 GA, 3 SV","athlete":{"id":"158626","displayName":"Emiliano Martínez","shortName":"E Martínez","fullName":"Emiliano Martínez","lastName":"Martínez","jersey":"23","team":{"id":"362"},"position":"G"}}]}],"neutralSite":false,"conferenceCompetition":false,"onDisneyNetwork":false,"appLinks":[{"rel":["summary","sportscenter","app","event"],"href":"sportscenter://x-callback-url/showGame?sportName=soccer&leagueAbbrev=eng.1&gameId=740697","text":"Summary","shortText":"Summary"}]},{"id":"740698","uid":"s:600~l:700~e:740698~c:740698","guid":"b2ec1ae9-cf80-36dc-ae5b-aa1ea236397e","date":"2025-11-09T14:00:00Z","timeValid":true,"recent":false,"name":"2025-26 English Premier League","shortName":"2025-26 English Premier League","links":[{"rel":["summary","desktop","event"],"href":"https://www.espn.com/soccer/match/_/gameId/740698/newcastle-united-brentford","text":"Summary"},{"rel":["recap","desktop","event"],"href":"https://www.espn.com/soccer/report/_/gameId/740698","text":"Report"},{"rel":["stats","desktop","event"],"href":"https://www.espn.com/soccer/matchstats/_/gameId/740698","text":"Statistics"}],"gamecastAvailable":true,"playByPlayAvailable":true,"commentaryAvailable":true,"wallclockAvailable":true,"fauxcastAvailable":false,"onWatch":false,"competitionId":"740698","location":"Gtech Community Stadium","season":2025,"seasonStartDate":"2025-06-01T04:00:00Z","seasonEndDate":"2026-06-01T03:59:00Z","seasonType":"1","seasonTypeHasGroups":false,"group":{"groupId":"1","name":"2025-26 English Premier League","abbreviation":"2025-26 English Premier League","shortName":"2025-26 English Premier League"},"link":"https://www.espn.com/soccer/match/_/gameId/740698/newcastle-united-brentford","status":"post","summary":"FT","period":2,"clock":"90'+12'","addedClock":720.0,"broadcasts":[{"typeId":4,"type":"STREAMING","isNational":true,"broadcasterId":789,"broadcastId":789,"name":"Peacock","shortName":"Peacock","callLetters":"Peacock","lang":"en","region":"us","slug":""}],"broadcast":"Peacock","odds":{"details":"NEW +140","overUnder":2.5,"spread":0.5,"overOdds":-130,"underOdds":100,"provider":{"id":"58","name":"ESPN BET","priority":1,"logos":[{"href":"https://a.espncdn.com/i/espnbet/ESPN_Bet_Sportsbook_Light.svg","rel":["light"]},{"href":"https://a.espncdn.com/i/espnbet/ESPN_Bet_Sportsbook_Dark.svg","rel":["dark"]}]},"home":{"moneyLine":175},"away":{"moneyLine":140},"draw":{"moneyLine":260},"awayTeamOdds":{"favorite":true,"favoriteAtOpen":false,"underdog":false,"moneyLine":140,"spreadOdds":125,"team":{"id":"361","abbreviation":"NEW","displayName":"Newcastle United","name":"Newcastle"}},"homeTeamOdds":{"favorite":false,"favoriteAtOpen":true,"underdog":true,"moneyLine":175,"spreadOdds":-175,"team":{"id":"337","abbreviation":"BRE","displayName":"Brentford","name":"Brentford"}},"drawOdds":{"moneyLine":260},"links":[{"language":"en-US","rel":["game","desktop","bets"],"href":"https://espnbet.app.link/integrations?%243p=a_espn&clr=espnbettingintegration&$canonical_url=/sport/soccer/organization/england/competition/premier-league/event/82cd8707-74b5-4ecf-8daa-55de7018241d","text":"Game","shortText":"Game","isExternal":true,"isPremium":false}],"pointSpread":{"displayName":"Spread","shortDisplayName":"Spread","home":{"open":{"line":"-0.5","odds":"+190"},"close":{"line":"+0.5","odds":"-175","outcome":"WIN","icon":"https://a.espncdn.com/i/espnbet/espn-bet-checkmark-bold.png","iconDark":"https://a.espncdn.com/i/espnbet/dark/espn-bet-checkmark-bold.png"},"current":{"line":"-1.5","odds":"+270"}},"away":{"open":{"line":"+0.5","odds":"-275"},"close":{"line":"-0.5","odds":"+125","outcome":"LOSS"},"current":{"line":"+1.5","odds":"-500"}}},"moneyline":{"displayName":"Moneyline","shortDisplayName":"ML","home":{"open":{"odds":"+205"},"close":{"odds":"+175","outcome":"WIN","icon":"https://a.espncdn.com/i/espnbet/espn-bet-checkmark-bold.png","iconDark":"https://a.espncdn.com/i/espnbet/dark/espn-bet-checkmark-bold.png"},"current":{"odds":"-3000"}},"away":{"open":{"odds":"+120"},"close":{"odds":"+140","outcome":"LOSS"},"current":{"odds":"+10000"}},"draw":{"open":{"odds":"+240"},"close":{"odds":"+260","outcome":"LOSS"},"current":{"odds":"+1100"}}},"total":{"displayName":"Total","shortDisplayName":"Total","over":{"open":{"line":"o2.5","odds":"-135"},"close":{"line":"o2.5","odds":"-130","outcome":"WIN","icon":"https://a.espncdn.com/i/espnbet/espn-bet-checkmark-bold.png","iconDark":"https://a.espncdn.com/i/espnbet/dark/espn-bet-checkmark-bold.png"},"current":{"line":"o4.5","odds":"+900"}},"under":{"open":{"line":"u2.5","odds":"EVEN"},"close":{"line":"u2.5","odds":"EVEN","outcome":"LOSS"},"current":{"line":"u4.5","odds":"-3500"}}},"header":{"logo":{"light":"https://a.espncdn.com/i/espnbet/espn-bet-square-off.svg","dark":"https://a.espncdn.com/i/espnbet/dark/espn-bet-square-off.svg","exclusivesLogoDark":"https://a.espncdn.com/i/espnbet/espn-bet-square-mint.svg","exclusivesLogoLight":"https://a.espncdn.com/i/espnbet/espn-bet-square-mint.svg"},"text":"ESPN Bet Sportsbook"}},"fullStatus":{"clock":5400.0,"addedClock":720.0,"displayClock":"90'+12'","period":2,"displayPeriod":"2nd","type":{"id":"28","name":"STATUS_FULL_TIME","state":"post","completed":true,"description":"Full Time","detail":"FT","shortDetail":"FT"}},"competitors":[{"id":"361","guid":"ec6b4352-98d3-424d-6214-778d79b47a01","uid":"s:600~t:361","type":"team","order":1,"homeAway":"away","winner":false,"form":"LWLWW","displayName":"Newcastle United","name":"Newcastle","abbreviation":"NEW","location":"Newcastle United","color":"000000","alternateColor":"cd1937","score":"1","isNational":false,"links":[{"language":"en-US","rel":["clubhouse","desktop","team"],"href":"https://www.espn.com/soccer/club/_/id/361/newcastle-united","text":"Clubhouse","shortText":"Clubhouse","isExternal":false,"isPremium":false,"isHidden":false},{"language":"en-US","rel":["stats","desktop","team"],"href":"https://www.espn.com/soccer/team/stats/_/id/361/newcastle-united","text":"Stats","shortText":"Stats","isExternal":false,"isPremium":false,"isHidden":false},{"language":"en-US","rel":["schedule","desktop","team"],"href":"https://www.espn.com/soccer/team/fixtures/_/id/361/newcastle-united","text":"Fixtures","shortText":"Fixtures","isExternal":false,"isPremium":false,"isHidden":false},{"language":"en-US","rel":["results","desktop","team"],"href":"https://www.espn.com/soccer/team/results/_/id/361/newcastle-united","text":"Results","shortText":"Results","isExternal":false,"isPremium":false,"isHidden":false},{"language":"en-US","rel":["standings","desktop","team"],"href":"https://www.espn.com/soccer/standings/_/league/eng.1","text":"Standings","shortText":"Standings","isExternal":false,"isPremium":false,"isHidden":false},{"language":"en-US","rel":["squad","desktop","team"],"href":"https://www.espn.com/soccer/team/squad/_/id/361/newcastle-united","text":"Squad","shortText":"Squad","isExternal":false,"isPremium":false,"isHidden":false}],"record":"3-3-5, 12 pts","records":[],"group":"1","recordStats":{"awayPointsFor":{"value":3.0},"pointsAgainst":{"value":14.0},"awayGamesPlayed":{"value":6.0},"awayWins":{"value":0.0},"losses":{"value":5.0},"points":{"value":12.0},"homeWins":{"value":3.0},"pointDifferential":{"value":-3.0},"homePointsAgainst":{"value":6.0},"gamesPlayed":{"value":11.0},"ties":{"value":3.0},"awayLosses":{"value":3.0},"rank":{"value":14.0},"homePointsFor":{"value":8.0},"awayTies":{"value":3.0},"wins":{"value":3.0},"homeTies":{"value":0.0},"pointsFor":{"value":11.0},"homeLosses":{"value":2.0},"streak":{"value":0.0},"homeGamesPlayed":{"value":5.0},"awayPointsAgainst":{"value":8.0}},"logo":"https://a.espncdn.com/i/teamlogos/soccer/500/361.png","logoDark":"https://a.espncdn.com/i/teamlogos/soccer/500-dark/361.png","goalieSummary":[{"displayValue":"1 GA, 3 SV","athlete":{"id":"161715","displayName":"Nick Pope","shortName":"N Pope","fullName":"Nick Pope","lastName":"Pope","jersey":"1","team":{"id":"361"},"position":"G"}}]},{"id":"337","guid":"0446e7fd-7655-f17a-d282-8c401b808d1f","uid":"s:600~t:337","type":"team","order":0,"homeAway":"home","winner":true,"form":"WLWWW","displayName":"Brentford","name":"Brentford","abbreviation":"BRE","location":"Brentford","color":"f42727","alternateColor":"f8ced9","score":"3","isNational":false,"links":[{"language":"en-US","rel":["clubhouse","desktop","team"],"href":"https://www.espn.com/soccer/club/_/id/337/brentford","text":"Clubhouse","shortText":"Clubhouse","isExternal":false,"isPremium":false,"isHidden":false},{"language":"en-US","rel":["stats","desktop","team"],"href":"https://www.espn.com/soccer/team/stats/_/id/337/brentford","text":"Stats","shortText":"Stats","isExternal":false,"isPremium":false,"isHidden":false},{"language":"en-US","rel":["schedule","desktop","team"],"href":"https://www.espn.com/soccer/team/fixtures/_/id/337/brentford","text":"Fixtures","shortText":"Fixtures","isExternal":false,"isPremium":false,"isHidden":false},{"language":"en-US","rel":["results","desktop","team"],"href":"https://www.espn.com/soccer/team/results/_/id/337/brentford","text":"Results","shortText":"Results","isExternal":false,"isPremium":false,"isHidden":false},{"language":"en-US","rel":["standings","desktop","team"],"href":"https://www.espn.com/soccer/standings/_/league/eng.1","text":"Standings","shortText":"Standings","isExternal":false,"isPremium":false,"isHidden":false},{"language":"en-US","rel":["squad","desktop","team"],"href":"https://www.espn.com/soccer/team/squad/_/id/337/brentford","text":"Squad","shortText":"Squad","isExternal":false,"isPremium":false,"isHidden":false}],"record":"5-1-5, 16 pts","records":[],"group":"1","recordStats":{"awayPointsFor":{"value":5.0},"pointsAgainst":{"value":17.0},"awayGamesPlayed":{"value":5.0},"awayWins":{"value":1.0},"losses":{"value":5.0},"points":{"value":16.0},"homeWins":{"value":4.0},"pointDifferential":{"value":0.0},"homePointsAgainst":{"value":7.0},"gamesPlayed":{"value":11.0},"ties":{"value":1.0},"awayLosses":{"value":4.0},"rank":{"value":12.0},"homePointsFor":{"value":12.0},"awayTies":{"value":0.0},"wins":{"value":5.0},"homeTies":{"value":1.0},"pointsFor":{"value":17.0},"homeLosses":{"value":1.0},"streak":{"value":0.0},"homeGamesPlayed":{"value":6.0},"awayPointsAgainst":{"value":10.0}},"logo":"https://a.espncdn.com/i/teamlogos/soccer/500/337.png","logoDark":"https://a.espncdn.com/i/teamlogos/soccer/500-dark/337.png","goalieSummary":[{"displayValue":"1 GA, 0 SV","athlete":{"id":"275599","displayName":"Caoimhín Kelleher","shortName":"C Kelleher","fullName":"Caoimhín Kelleher","lastName":"Kelleher","jersey":"1","team":{"id":"337"},"position":"G"}}]}],"neutralSite":false,"conferenceCompetition":false,"onDisneyNetwork":false,"appLinks":[{"rel":["summary","sportscenter","app","event"],"href":"sportscenter://x-callback-url/showGame?sportName=soccer&leagueAbbrev=eng.1&gameId=740698","text":"Summary","shortText":"Summary"}]},{"id":"740700","uid":"s:600~l:700~e:740700~c:740700","guid":"1d9cbc19-82a3-33cc-9d19-935ebd5a418e","date":"2025-11-09T14:00:00Z","timeValid":true,"recent":false,"name":"2025-26 English Premier League","shortName":"2025-26 English Premier League","links":[{"rel":["summary","desktop","event"],"href":"https://www.espn.com/soccer/match/_/gameId/740700/brighton-hove-albion-crystal-palace","text":"Summary"},{"rel":["recap","desktop","event"],"href":"https://www.espn.com/soccer/report/_/gameId/740700","text":"Report"},{"rel":["stats","desktop","event"],"href":"https://www.espn.com/soccer/matchstats/_/gameId/740700","text":"Statistics"}],"gamecastAvailable":true,"playByPlayAvailable":true,"commentaryAvailable":true,"wallclockAvailable":true,"fauxcastAvailable":false,"onWatch":false,"competitionId":"740700","location":"Selhurst Park","season":2025,"seasonStartDate":"2025-06-01T04:00:00Z","seasonEndDate":"2026-06-01T03:59:00Z","seasonType":"1","seasonTypeHasGroups":false,"group":{"groupId":"1","name":"2025-26 English Premier League","abbreviation":"2025-26 English Premier League","shortName":"2025-26 English Premier League"},"link":"https://www.espn.com/soccer/match/_/gameId/740700/brighton-hove-albion-crystal-palace","status":"post","summary":"FT","period":2,"clock":"90'+9'","addedClock":540.0,"broadcasts":[{"typeId":4,"type":"STREAMING","isNational":true,"broadcasterId":789,"broadcastId":789,"name":"Peacock","shortName":"Peacock","callLetters":"Peacock","lang":"en","region":"us","slug":""}],"broadcast":"Peacock","odds":{"details":"CRY +135","overUnder":2.5,"spread":-0.5,"overOdds":-130,"underOdds":100,"provider":{"id":"58","name":"ESPN BET","priority":1,"logos":[{"href":"https://a.espncdn.com/i/espnbet/ESPN_Bet_Sportsbook_Light.svg","rel":["light"]},{"href":"https://a.espncdn.com/i/espnbet/ESPN_Bet_Sportsbook_Dark.svg","rel":["dark"]}]},"home":{"moneyLine":135},"away":{"moneyLine":200},"draw":{"moneyLine":235},"awayTeamOdds":{"favorite":false,"favoriteAtOpen":false,"underdog":true,"moneyLine":200,"spreadOdds":-165,"team":{"id":"331","abbreviation":"BHA","displayName":"Brighton & Hove Albion","name":"Brighton"}},"homeTeamOdds":{"favorite":true,"favoriteAtOpen":true,"underdog":false,"moneyLine":135,"spreadOdds":120,"team":{"id":"384","abbreviation":"CRY","displayName":"Crystal Palace","name":"C Palace"}},"drawOdds":{"moneyLine":235},"links":[{"language":"en-US","rel":["game","desktop","bets"],"href":"https://espnbet.app.link/integrations?%243p=a_espn&clr=espnbettingintegration&$canonical_url=/sport/soccer/organization/england/competition/premier-league/event/d04a9c8f-e46b-488b-b9b4-dc5cc785858f","text":"Game","shortText":"Game","isExternal":true,"isPremium":false}],"pointSpread":{"displayName":"Spread","shortDisplayName":"Spread","home":{"open":{"line":"-1.5","odds":"+290"},"close":{"line":"-0.5","odds":"+120","outcome":"LOSS"},"current":{"line":"-0.5","odds":"+400"}},"away":{"open":{"line":"+1.5","odds":"-500"},"close":{"line":"+0.5","odds":"-165","outcome":"WIN","icon":"https://a.espncdn.com/i/espnbet/espn-bet-checkmark-bold.png","iconDark":"https://a.espncdn.com/i/espnbet/dark/espn-bet-checkmark-bold.png"},"current":{"line":"+0.5","odds":"-1200"}}},"moneyline":{"displayName":"Moneyline","shortDisplayName":"ML","home":{"open":{"odds":"+115"},"close":{"odds":"+135","outcome":"LOSS"},"current":{"odds":"+2100"}},"away":{"open":{"odds":"+215"},"close":{"odds":"+200","outcome":"LOSS"},"current":{"odds":"+2300"}},"draw":{"open":{"odds":"+245"},"close":{"odds":"+235","outcome":"WIN","icon":"https://a.espncdn.com/i/espnbet/espn-bet-checkmark-bold.png","iconDark":"https://a.espncdn.com/i/espnbet/dark/espn-bet-checkmark-bold.png"},"current":{"odds":"-10000"}}},"total":{"displayName":"Total","shortDisplayName":"Total","over":{"open":{"line":"o5.5","odds":"+800"},"close":{"line":"o2.5","odds":"-130","outcome":"LOSS"},"current":{"line":"o0.5","odds":"+1100"}},"under":{"open":{"line":"u5.5","odds":"-1750"},"close":{"line":"u2.5","odds":"EVEN","outcome":"WIN","icon":"https://a.espncdn.com/i/espnbet/espn-bet-checkmark-bold.png","iconDark":"https://a.espncdn.com/i/espnbet/dark/espn-bet-checkmark-bold.png"},"current":{"line":"u0.5","odds":"-5000"}}},"header":{"logo":{"light":"https://a.espncdn.com/i/espnbet/espn-bet-square-off.svg","dark":"https://a.espncdn.com/i/espnbet/dark/espn-bet-square-off.svg","exclusivesLogoDark":"https://a.espncdn.com/i/espnbet/espn-bet-square-mint.svg","exclusivesLogoLight":"https://a.espncdn.com/i/espnbet/espn-bet-square-mint.svg"},"text":"ESPN Bet Sportsbook"}},"fullStatus":{"clock":5400.0,"addedClock":540.0,"displayClock":"90'+9'","period":2,"displayPeriod":"2nd","type":{"id":"28","name":"STATUS_FULL_TIME","state":"post","completed":true,"description":"Full Time","detail":"FT","shortDetail":"FT"}},"competitors":[{"id":"331","guid":"78c91a3f-9e5e-c8fe-8fca-778e97cb021a","uid":"s:600~t:331","type":"team","order":1,"homeAway":"away","winner":false,"form":"DWLLW","displayName":"Brighton & Hove Albion","name":"Brighton","abbreviation":"BHA","location":"Brighton & Hove Albion","color":"0606fa","alternateColor":"ffdd00","score":"0","isNational":false,"links":[{"language":"en-US","rel":["clubhouse","desktop","team"],"href":"https://www.espn.com/soccer/club/_/id/331/brighton-hove-albion","text":"Clubhouse","shortText":"Clubhouse","isExternal":false,"isPremium":false,"isHidden":false},{"language":"en-US","rel":["stats","desktop","team"],"href":"https://www.espn.com/soccer/team/stats/_/id/331/brighton-hove-albion","text":"Stats","shortText":"Stats","isExternal":false,"isPremium":false,"isHidden":false},{"language":"en-US","rel":["schedule","desktop","team"],"href":"https://www.espn.com/soccer/team/fixtures/_/id/331/brighton-hove-albion","text":"Fixtures","shortText":"Fixtures","isExternal":false,"isPremium":false,"isHidden":false},{"language":"en-US","rel":["results","desktop","team"],"href":"https://www.espn.com/soccer/team/results/_/id/331/brighton-hove-albion","text":"Results","shortText":"Results","isExternal":false,"isPremium":false,"isHidden":false},{"language":"en-US","rel":["standings","desktop","team"],"href":"https://www.espn.com/soccer/standings/_/league/eng.1","text":"Standings","shortText":"Standings","isExternal":false,"isPremium":false,"isHidden":false},{"language":"en-US","rel":["squad","desktop","team"],"href":"https://www.espn.com/soccer/team/squad/_/id/331/brighton-hove-albion","text":"Squad","shortText":"Squad","isExternal":false,"isPremium":false,"isHidden":false}],"record":"4-4-3, 16 pts","records":[],"group":"1","recordStats":{"awayPointsFor":{"value":7.0},"pointsAgainst":{"value":15.0},"awayGamesPlayed":{"value":6.0},"awayWins":{"value":1.0},"losses":{"value":3.0},"points":{"value":16.0},"homeWins":{"value":3.0},"pointDifferential":{"value":2.0},"homePointsAgainst":{"value":5.0},"gamesPlayed":{"value":11.0},"ties":{"value":4.0},"awayLosses":{"value":3.0},"rank":{"value":11.0},"homePointsFor":{"value":10.0},"awayTies":{"value":2.0},"wins":{"value":4.0},"homeTies":{"value":2.0},"pointsFor":{"value":17.0},"homeLosses":{"value":0.0},"streak":{"value":0.0},"homeGamesPlayed":{"value":5.0},"awayPointsAgainst":{"value":10.0}},"logo":"https://a.espncdn.com/i/teamlogos/soccer/500/331.png","logoDark":"https://a.espncdn.com/i/teamlogos/soccer/500-dark/331.png","goalieSummary":[{"displayValue":"0 GA, 2 SV","athlete":{"id":"291609","displayName":"Bart Verbruggen","shortName":"B Verbruggen","fullName":"Bart Verbruggen","lastName":"Verbruggen","jersey":"1","team":{"id":"331"},"position":"G"}}]},{"id":"384","guid":"e8703d92-a160-9bbf-cb81-1be6f3fd7969","uid":"s:600~t:384","type":"team","order":0,"homeAway":"home","winner":false,"form":"DWWWL","displayName":"Crystal Palace","name":"C Palace","abbreviation":"CRY","location":"Crystal Palace","color":"0202fb","alternateColor":"ffdd00","score":"0","isNational":false,"links":[{"language":"en-US","rel":["clubhouse","desktop","team"],"href":"https://www.espn.com/soccer/club/_/id/384/crystal-palace","text":"Clubhouse","shortText":"Clubhouse","isExternal":false,"isPremium":false,"isHidden":false},{"language":"en-US","rel":["stats","desktop","team"],"href":"https://www.espn.com/soccer/team/stats/_/id/384/crystal-palace","text":"Stats","shortText":"Stats","isExternal":false,"isPremium":false,"isHidden":false},{"language":"en-US","rel":["schedule","desktop","team"],"href":"https://www.espn.com/soccer/team/fixtures/_/id/384/crystal-palace","text":"Fixtures","shortText":"Fixtures","isExternal":false,"isPremium":false,"isHidden":false},{"language":"en-US","rel":["results","desktop","team"],"href":"https://www.espn.com/soccer/team/results/_/id/384/crystal-palace","text":"Results","shortText":"Results","isExternal":false,"isPremium":false,"isHidden":false},{"language":"en-US","rel":["standings","desktop","team"],"href":"https://www.espn.com/soccer/standings/_/league/eng.1","text":"Standings","shortText":"Standings","isExternal":false,"isPremium":false,"isHidden":false},{"language":"en-US","rel":["squad","desktop","team"],"href":"https://www.espn.com/soccer/team/squad/_/id/384/crystal-palace","text":"Squad","shortText":"Squad","isExternal":false,"isPremium":false,"isHidden":false}],"record":"4-5-2, 17 pts","records":[],"group":"1","recordStats":{"awayPointsFor":{"value":6.0},"pointsAgainst":{"value":9.0},"awayGamesPlayed":{"value":5.0},"awayWins":{"value":2.0},"losses":{"value":2.0},"points":{"value":17.0},"homeWins":{"value":2.0},"pointDifferential":{"value":5.0},"homePointsAgainst":{"value":5.0},"gamesPlayed":{"value":11.0},"ties":{"value":5.0},"awayLosses":{"value":2.0},"rank":{"value":10.0},"homePointsFor":{"value":8.0},"awayTies":{"value":1.0},"wins":{"value":4.0},"homeTies":{"value":4.0},"pointsFor":{"value":14.0},"homeLosses":{"value":0.0},"streak":{"value":0.0},"homeGamesPlayed":{"value":6.0},"awayPointsAgainst":{"value":4.0}},"logo":"https://a.espncdn.com/i/teamlogos/soccer/500/384.png","logoDark":"https://a.espncdn.com/i/teamlogos/soccer/500-dark/384.png","goalieSummary":[{"displayValue":"0 GA, 3 SV","athlete":{"id":"234172","displayName":"Dean Henderson","shortName":"D Henderson","fullName":"Dean Henderson","lastName":"Henderson","jersey":"1","team":{"id":"384"},"position":"G"}}]}],"neutralSite":false,"conferenceCompetition":false,"onDisneyNetwork":false,"appLinks":[{"rel":["summary","sportscenter","app","event"],"href":"sportscenter://x-callback-url/showGame?sportName=soccer&leagueAbbrev=eng.1&gameId=740700","text":"Summary","shortText":"Summary"}]},{"id":"740703","uid":"s:600~l:700~e:740703~c:740703","guid":"bae1e9c6-b576-3191-80eb-5489a7671c9c","date":"2025-11-09T14:00:00Z","timeValid":true,"recent":false,"name":"2025-26 English Premier League","shortName":"2025-26 English Premier League","links":[{"rel":["summary","desktop","event"],"href":"https://www.espn.com/soccer/match/_/gameId/740703/leeds-united-nottingham-forest","text":"Summary"},{"rel":["recap","desktop","event"],"href":"https://www.espn.com/soccer/report/_/gameId/740703","text":"Report"},{"rel":["stats","desktop","event"],"href":"https://www.espn.com/soccer/matchstats/_/gameId/740703","text":"Statistics"}],"gamecastAvailable":true,"playByPlayAvailable":true,"commentaryAvailable":true,"wallclockAvailable":true,"fauxcastAvailable":false,"onWatch":false,"competitionId":"740703","location":"The City Ground","season":2025,"seasonStartDate":"2025-06-01T04:00:00Z","seasonEndDate":"2026-06-01T03:59:00Z","seasonType":"1","seasonTypeHasGroups":false,"group":{"groupId":"1","name":"2025-26 English Premier League","abbreviation":"2025-26 English Premier League","shortName":"2025-26 English Premier League"},"link":"https://www.espn.com/soccer/match/_/gameId/740703/leeds-united-nottingham-forest","status":"post","summary":"FT","period":2,"clock":"90'+7'","addedClock":420.0,"broadcasts":[{"typeId":4,"type":"STREAMING","isNational":true,"broadcasterId":789,"broadcastId":789,"name":"Peacock","shortName":"Peacock","callLetters":"Peacock","lang":"en","region":"us","slug":""}],"broadcast":"Peacock","odds":{"details":"NFO +120","overUnder":2.5,"spread":-0.5,"overOdds":135,"underOdds":-180,"provider":{"id":"58","name":"ESPN BET","priority":1,"logos":[{"href":"https://a.espncdn.com/i/espnbet/ESPN_Bet_Sportsbook_Light.svg","rel":["light"]},{"href":"https://a.espncdn.com/i/espnbet/ESPN_Bet_Sportsbook_Dark.svg","rel":["dark"]}]},"home":{"moneyLine":120},"away":{"moneyLine":260},"draw":{"moneyLine":205},"awayTeamOdds":{"favorite":false,"favoriteAtOpen":false,"underdog":true,"moneyLine":260,"spreadOdds":-155,"team":{"id":"357","abbreviation":"LEE","displayName":"Leeds United","name":"Leeds"}},"homeTeamOdds":{"favorite":true,"favoriteAtOpen":true,"underdog":false,"moneyLine":120,"spreadOdds":110,"team":{"id":"393","abbreviation":"NFO","displayName":"Nottingham Forest","name":"Nottm Forest"}},"drawOdds":{"moneyLine":205},"links":[{"language":"en-US","rel":["game","desktop","bets"],"href":"https://espnbet.app.link/integrations?%243p=a_espn&clr=espnbettingintegration&$canonical_url=/sport/soccer/organization/england/competition/premier-league/event/451c632f-57b1-45ae-86a0-f1542f1e0962","text":"Game","shortText":"Game","isExternal":true,"isPremium":false}],"pointSpread":{"displayName":"Spread","shortDisplayName":"Spread","home":{"open":{"line":"-0.5","odds":"EVEN"},"close":{"line":"-0.5","odds":"+110","outcome":"WIN","icon":"https://a.espncdn.com/i/espnbet/espn-bet-checkmark-bold.png","iconDark":"https://a.espncdn.com/i/espnbet/dark/espn-bet-checkmark-bold.png"},"current":{"line":"-1.5","odds":"-300"}},"away":{"open":{"line":"+0.5","odds":"-140"},"close":{"line":"+0.5","odds":"-155","outcome":"LOSS"},"current":{"line":"+1.5","odds":"+200"}}},"moneyline":{"displayName":"Moneyline","shortDisplayName":"ML","home":{"open":{"odds":"+110"},"close":{"odds":"+120","outcome":"WIN","icon":"https://a.espncdn.com/i/espnbet/espn-bet-checkmark-bold.png","iconDark":"https://a.espncdn.com/i/espnbet/dark/espn-bet-checkmark-bold.png"},"current":{"odds":"-50000"}},"away":{"open":{"odds":"+250"},"close":{"odds":"+260","outcome":"LOSS"},"current":{"odds":"+10000"}},"draw":{"open":{"odds":"+225"},"close":{"odds":"+205","outcome":"LOSS"},"current":{"odds":"+2100"}}},"total":{"displayName":"Total","shortDisplayName":"Total","over":{"open":{"line":"o2.5","odds":"EVEN"},"close":{"line":"o2.5","odds":"+135","outcome":"WIN","icon":"https://a.espncdn.com/i/espnbet/espn-bet-checkmark-bold.png","iconDark":"https://a.espncdn.com/i/espnbet/dark/espn-bet-checkmark-bold.png"},"current":{"line":"o4.5","odds":"+1100"}},"under":{"open":{"line":"u2.5","odds":"-140"},"close":{"line":"u2.5","odds":"-180","outcome":"LOSS"},"current":{"line":"u4.5","odds":"-5000"}}},"header":{"logo":{"light":"https://a.espncdn.com/i/espnbet/espn-bet-square-off.svg","dark":"https://a.espncdn.com/i/espnbet/dark/espn-bet-square-off.svg","exclusivesLogoDark":"https://a.espncdn.com/i/espnbet/espn-bet-square-mint.svg","exclusivesLogoLight":"https://a.espncdn.com/i/espnbet/espn-bet-square-mint.svg"},"text":"ESPN Bet Sportsbook"}},"fullStatus":{"clock":5400.0,"addedClock":420.0,"displayClock":"90'+7'","period":2,"displayPeriod":"2nd","type":{"id":"28","name":"STATUS_FULL_TIME","state":"post","completed":true,"description":"Full Time","detail":"FT","shortDetail":"FT"}},"competitors":[{"id":"357","guid":"231a0077-e0f5-f148-974b-82b9ec5f304e","uid":"s:600~t:357","type":"team","order":1,"homeAway":"away","winner":false,"form":"LLWLL","displayName":"Leeds United","name":"Leeds","abbreviation":"LEE","location":"Leeds United","color":"ffffff","alternateColor":"ffff00","score":"1","isNational":false,"links":[{"language":"en-US","rel":["clubhouse","desktop","team"],"href":"https://www.espn.com/soccer/club/_/id/357/leeds-united","text":"Clubhouse","shortText":"Clubhouse","isExternal":false,"isPremium":false,"isHidden":false},{"language":"en-US","rel":["stats","desktop","team"],"href":"https://www.espn.com/soccer/team/stats/_/id/357/leeds-united","text":"Stats","shortText":"Stats","isExternal":false,"isPremium":false,"isHidden":false},{"language":"en-US","rel":["schedule","desktop","team"],"href":"https://www.espn.com/soccer/team/fixtures/_/id/357/leeds-united","text":"Fixtures","shortText":"Fixtures","isExternal":false,"isPremium":false,"isHidden":false},{"language":"en-US","rel":["results","desktop","team"],"href":"https://www.espn.com/soccer/team/results/_/id/357/leeds-united","text":"Results","shortText":"Results","isExternal":false,"isPremium":false,"isHidden":false},{"language":"en-US","rel":["standings","desktop","team"],"href":"https://www.espn.com/soccer/standings/_/league/eng.1","text":"Standings","shortText":"Standings","isExternal":false,"isPremium":false,"isHidden":false},{"language":"en-US","rel":["squad","desktop","team"],"href":"https://www.espn.com/soccer/team/squad/_/id/357/leeds-united","text":"Squad","shortText":"Squad","isExternal":false,"isPremium":false,"isHidden":false}],"record":"3-2-6, 11 pts","records":[],"group":"1","recordStats":{"awayPointsFor":{"value":4.0},"pointsAgainst":{"value":20.0},"awayGamesPlayed":{"value":6.0},"awayWins":{"value":1.0},"losses":{"value":6.0},"points":{"value":11.0},"homeWins":{"value":2.0},"pointDifferential":{"value":-10.0},"homePointsAgainst":{"value":5.0},"gamesPlayed":{"value":11.0},"ties":{"value":2.0},"awayLosses":{"value":5.0},"rank":{"value":16.0},"homePointsFor":{"value":6.0},"awayTies":{"value":0.0},"wins":{"value":3.0},"homeTies":{"value":2.0},"pointsFor":{"value":10.0},"homeLosses":{"value":1.0},"streak":{"value":0.0},"homeGamesPlayed":{"value":5.0},"awayPointsAgainst":{"value":15.0}},"logo":"https://a.espncdn.com/i/teamlogos/soccer/500/357.png","logoDark":"https://a.espncdn.com/i/teamlogos/soccer/500-dark/357.png","goalieSummary":[{"displayValue":"3 GA, 3 SV","athlete":{"id":"252406","displayName":"Lucas Perri","shortName":"L Perri","fullName":"Lucas Perri","lastName":"Perri","jersey":"1","team":{"id":"357"},"position":"G"}}]},{"id":"393","guid":"ad9ef79b-ca27-077e-8a6f-335e0d220b27","uid":"s:600~t:393","type":"team","order":0,"homeAway":"home","winner":true,"form":"WDDLW","displayName":"Nottingham Forest","name":"Nottm Forest","abbreviation":"NFO","location":"Nottingham Forest","color":"c8102e","alternateColor":"132257","score":"3","isNational":false,"links":[{"language":"en-US","rel":["clubhouse","desktop","team"],"href":"https://www.espn.com/soccer/club/_/id/393/nottingham-forest","text":"Clubhouse","shortText":"Clubhouse","isExternal":false,"isPremium":false,"isHidden":false},{"language":"en-US","rel":["stats","desktop","team"],"href":"https://www.espn.com/soccer/team/stats/_/id/393/nottingham-forest","text":"Stats","shortText":"Stats","isExternal":false,"isPremium":false,"isHidden":false},{"language":"en-US","rel":["schedule","desktop","team"],"href":"https://www.espn.com/soccer/team/fixtures/_/id/393/nottingham-forest","text":"Fixtures","shortText":"Fixtures","isExternal":false,"isPremium":false,"isHidden":false},{"language":"en-US","rel":["results","desktop","team"],"href":"https://www.espn.com/soccer/team/results/_/id/393/nottingham-forest","text":"Results","shortText":"Results","isExternal":false,"isPremium":false,"isHidden":false},{"language":"en-US","rel":["standings","desktop","team"],"href":"https://www.espn.com/soccer/standings/_/league/eng.1","text":"Standings","shortText":"Standings","isExternal":false,"isPremium":false,"isHidden":false},{"language":"en-US","rel":["squad","desktop","team"],"href":"https://www.espn.com/soccer/team/squad/_/id/393/nottingham-forest","text":"Squad","shortText":"Squad","isExternal":false,"isPremium":false,"isHidden":false}],"record":"2-3-6, 9 pts","records":[],"group":"1","recordStats":{"awayPointsFor":{"value":2.0},"pointsAgainst":{"value":20.0},"awayGamesPlayed":{"value":5.0},"awayWins":{"value":0.0},"losses":{"value":6.0},"points":{"value":9.0},"homeWins":{"value":2.0},"pointDifferential":{"value":-10.0},"homePointsAgainst":{"value":11.0},"gamesPlayed":{"value":11.0},"ties":{"value":3.0},"awayLosses":{"value":3.0},"rank":{"value":19.0},"homePointsFor":{"value":8.0},"awayTies":{"value":2.0},"wins":{"value":2.0},"homeTies":{"value":1.0},"pointsFor":{"value":10.0},"homeLosses":{"value":3.0},"streak":{"value":0.0},"homeGamesPlayed":{"value":6.0},"awayPointsAgainst":{"value":9.0}},"logo":"https://a.espncdn.com/i/teamlogos/soccer/500/393.png","logoDark":"https://a.espncdn.com/i/teamlogos/soccer/500-dark/393.png","goalieSummary":[{"displayValue":"1 GA, 2 SV","athlete":{"id":"179497","displayName":"Matz Sels","shortName":"M Sels","fullName":"Matz Sels","lastName":"Sels","jersey":"26","team":{"id":"393"},"position":"G"}}]}],"neutralSite":false,"conferenceCompetition":false,"onDisneyNetwork":false,"appLinks":[{"rel":["summary","sportscenter","app","event"],"href":"sportscenter://x-callback-url/showGame?sportName=soccer&leagueAbbrev=eng.1&gameId=740703","text":"Summary","shortText":"Summary"}]},{"id":"740702","uid":"s:600~l:700~e:740702~c:740702","guid":"6d62b30e-0590-3f2c-b2ec-2ca3672ce0b4","date":"2025-11-09T16:30:00Z","timeValid":true,"recent":false,"name":"2025-26 English Premier League","shortName":"2025-26 English Premier League","links":[{"rel":["summary","desktop","event"],"href":"https://www.espn.com/soccer/match/_/gameId/740702/liverpool-manchester-city","text":"Summary"},{"rel":["recap","desktop","event"],"href":"https://www.espn.com/soccer/report/_/gameId/740702","text":"Report"},{"rel":["stats","desktop","event"],"href":"https://www.espn.com/soccer/matchstats/_/gameId/740702","text":"Statistics"}],"gamecastAvailable":true,"playByPlayAvailable":true,"commentaryAvailable":true,"wallclockAvailable":true,"fauxcastAvailable":false,"onWatch":false,"competitionId":"740702","location":"Etihad Stadium","season":2025,"seasonStartDate":"2025-06-01T04:00:00Z","seasonEndDate":"2026-06-01T03:59:00Z","seasonType":"1","seasonTypeHasGroups":false,"group":{"groupId":"1","name":"2025-26 English Premier League","abbreviation":"2025-26 English Premier League","shortName":"2025-26 English Premier League"},"link":"https://www.espn.com/soccer/match/_/gameId/740702/liverpool-manchester-city","status":"post","summary":"FT","period":2,"clock":"90'+4'","addedClock":240.0,"broadcasts":[{"typeId":1,"type":"TV","isNational":true,"broadcasterId":519,"broadcastId":519,"name":"USA Network","shortName":"USA Net","callLetters":"USA Net","lang":"en","region":"us","slug":""},{"typeId":1,"type":"TV","isNational":true,"broadcasterId":488,"broadcastId":488,"name":"Telemundo","shortName":"Tele","callLetters":"Tele","lang":"en","region":"us","slug":""}],"broadcast":"USA Net/Tele","odds":{"details":"MNC -115","overUnder":3.5,"spread":-0.5,"overOdds":110,"underOdds":-140,"provider":{"id":"58","name":"ESPN BET","priority":1,"logos":[{"href":"https://a.espncdn.com/i/espnbet/ESPN_Bet_Sportsbook_Light.svg","rel":["light"]},{"href":"https://a.espncdn.com/i/espnbet/ESPN_Bet_Sportsbook_Dark.svg","rel":["dark"]}]},"home":{"moneyLine":-115},"away":{"moneyLine":270},"draw":{"moneyLine":290},"awayTeamOdds":{"favorite":false,"favoriteAtOpen":true,"underdog":true,"moneyLine":270,"spreadOdds":-115,"team":{"id":"364","abbreviation":"LIV","displayName":"Liverpool","name":"Liverpool"}},"homeTeamOdds":{"favorite":true,"favoriteAtOpen":false,"underdog":false,"moneyLine":-115,"spreadOdds":-120,"team":{"id":"382","abbreviation":"MNC","displayName":"Manchester City","name":"Man City"}},"drawOdds":{"moneyLine":290},"links":[{"language":"en-US","rel":["game","desktop","bets"],"href":"https://espnbet.app.link/integrations?%243p=a_espn&clr=espnbettingintegration&$canonical_url=/sport/soccer/organization/england/competition/premier-league/event/1bd00b1d-1de5-4103-8cce-6792e1a4b2fd","text":"Game","shortText":"Game","isExternal":true,"isPremium":false}],"pointSpread":{"displayName":"Spread","shortDisplayName":"Spread","home":{"open":{"line":"+1.5","odds":"-1300"},"close":{"line":"-0.5","odds":"-120","outcome":"WIN","icon":"https://a.espncdn.com/i/espnbet/espn-bet-checkmark-bold.png","iconDark":"https://a.espncdn.com/i/espnbet/dark/espn-bet-checkmark-bold.png"},"current":{"line":"-3.5","odds":"+400"}},"away":{"open":{"line":"-1.5","odds":"+600"},"close":{"line":"+0.5","odds":"-115","outcome":"LOSS"},"current":{"line":"+3.5","odds":"-1200"}}},"moneyline":{"displayName":"Moneyline","shortDisplayName":"ML","home":{"open":{"odds":"-125"},"close":{"odds":"-115","outcome":"WIN","icon":"https://a.espncdn.com/i/espnbet/espn-bet-checkmark-bold.png","iconDark":"https://a.espncdn.com/i/espnbet/dark/espn-bet-checkmark-bold.png"},"current":{"odds":"OFF"}},"away":{"open":{"odds":"+280"},"close":{"odds":"+270","outcome":"LOSS"},"current":{"odds":"+10000"}},"draw":{"open":{"odds":"+280"},"close":{"odds":"+290","outcome":"LOSS"},"current":{"odds":"+3300"}}},"total":{"displayName":"Total","shortDisplayName":"Total","over":{"open":{"line":"o4.5","odds":"+290"},"close":{"line":"o3.5","odds":"+110","outcome":"LOSS"},"current":{"line":"o3.5","odds":"+1100"}},"under":{"open":{"line":"u4.5","odds":"-475"},"close":{"line":"u3.5","odds":"-140","outcome":"WIN","icon":"https://a.espncdn.com/i/espnbet/espn-bet-checkmark-bold.png","iconDark":"https://a.espncdn.com/i/espnbet/dark/espn-bet-checkmark-bold.png"},"current":{"line":"u3.5","odds":"-5000"}}},"header":{"logo":{"light":"https://a.espncdn.com/i/espnbet/espn-bet-square-off.svg","dark":"https://a.espncdn.com/i/espnbet/dark/espn-bet-square-off.svg","exclusivesLogoDark":"https://a.espncdn.com/i/espnbet/espn-bet-square-mint.svg","exclusivesLogoLight":"https://a.espncdn.com/i/espnbet/espn-bet-square-mint.svg"},"text":"ESPN Bet Sportsbook"}},"fullStatus":{"clock":5400.0,"addedClock":240.0,"displayClock":"90'+4'","period":2,"displayPeriod":"2nd","type":{"id":"28","name":"STATUS_FULL_TIME","state":"post","completed":true,"description":"Full Time","detail":"FT","shortDetail":"FT"}},"competitors":[{"id":"364","guid":"a47fbcec-c948-cf4c-9e41-3dfa37588c9c","uid":"s:600~t:364","type":"team","order":1,"homeAway":"away","winner":false,"form":"LWWLL","displayName":"Liverpool","name":"Liverpool","abbreviation":"LIV","location":"Liverpool","color":"d11317","alternateColor":"132257","score":"0","isNational":false,"links":[{"language":"en-US","rel":["clubhouse","desktop","team"],"href":"https://www.espn.com/soccer/club/_/id/364/liverpool","text":"Clubhouse","shortText":"Clubhouse","isExternal":false,"isPremium":false,"isHidden":false},{"language":"en-US","rel":["stats","desktop","team"],"href":"https://www.espn.com/soccer/team/stats/_/id/364/liverpool","text":"Stats","shortText":"Stats","isExternal":false,"isPremium":false,"isHidden":false},{"language":"en-US","rel":["schedule","desktop","team"],"href":"https://www.espn.com/soccer/team/fixtures/_/id/364/liverpool","text":"Fixtures","shortText":"Fixtures","isExternal":false,"isPremium":false,"isHidden":false},{"language":"en-US","rel":["results","desktop","team"],"href":"https://www.espn.com/soccer/team/results/_/id/364/liverpool","text":"Results","shortText":"Results","isExternal":false,"isPremium":false,"isHidden":false},{"language":"en-US","rel":["standings","desktop","team"],"href":"https://www.espn.com/soccer/standings/_/league/eng.1","text":"Standings","shortText":"Standings","isExternal":false,"isPremium":false,"isHidden":false},{"language":"en-US","rel":["squad","desktop","team"],"href":"https://www.espn.com/soccer/team/squad/_/id/364/liverpool","text":"Squad","shortText":"Squad","isExternal":false,"isPremium":false,"isHidden":false}],"record":"6-0-5, 18 pts","records":[],"group":"1","recordStats":{"awayPointsFor":{"value":8.0},"pointsAgainst":{"value":17.0},"awayGamesPlayed":{"value":6.0},"awayWins":{"value":2.0},"losses":{"value":5.0},"points":{"value":18.0},"homeWins":{"value":4.0},"pointDifferential":{"value":1.0},"homePointsAgainst":{"value":5.0},"gamesPlayed":{"value":11.0},"ties":{"value":0.0},"awayLosses":{"value":4.0},"rank":{"value":8.0},"homePointsFor":{"value":10.0},"awayTies":{"value":0.0},"wins":{"value":6.0},"homeTies":{"value":0.0},"pointsFor":{"value":18.0},"homeLosses":{"value":1.0},"streak":{"value":0.0},"homeGamesPlayed":{"value":5.0},"awayPointsAgainst":{"value":12.0}},"logo":"https://a.espncdn.com/i/teamlogos/soccer/500/364.png","logoDark":"https://a.espncdn.com/i/teamlogos/soccer/500-dark/364.png","goalieSummary":[{"displayValue":"3 GA, 3 SV","athlete":{"id":"274742","displayName":"Giorgi Mamardashvili","shortName":"G Mamardashvili","fullName":"Giorgi Mamardashvili","lastName":"Mamardashvili","jersey":"25","team":{"id":"364"},"position":"G"}}]},{"id":"382","guid":"94fd5d7e-35b1-9d52-c9f2-4a37259bea36","uid":"s:600~t:382","type":"team","order":0,"homeAway":"home","winner":true,"form":"WWWWL","displayName":"Manchester City","name":"Man City","abbreviation":"MNC","location":"Manchester City","color":"99c5ea","alternateColor":"e6ff00","score":"3","isNational":false,"links":[{"language":"en-US","rel":["clubhouse","desktop","team"],"href":"https://www.espn.com/soccer/club/_/id/382/manchester-city","text":"Clubhouse","shortText":"Clubhouse","isExternal":false,"isPremium":false,"isHidden":false},{"language":"en-US","rel":["stats","desktop","team"],"href":"https://www.espn.com/soccer/team/stats/_/id/382/manchester-city","text":"Stats","shortText":"Stats","isExternal":false,"isPremium":false,"isHidden":false},{"language":"en-US","rel":["schedule","desktop","team"],"href":"https://www.espn.com/soccer/team/fixtures/_/id/382/manchester-city","text":"Fixtures","shortText":"Fixtures","isExternal":false,"isPremium":false,"isHidden":false},{"language":"en-US","rel":["results","desktop","team"],"href":"https://www.espn.com/soccer/team/results/_/id/382/manchester-city","text":"Results","shortText":"Results","isExternal":false,"isPremium":false,"isHidden":false},{"language":"en-US","rel":["standings","desktop","team"],"href":"https://www.espn.com/soccer/standings/_/league/eng.1","text":"Standings","shortText":"Standings","isExternal":false,"isPremium":false,"isHidden":false},{"language":"en-US","rel":["squad","desktop","team"],"href":"https://www.espn.com/soccer/team/squad/_/id/382/manchester-city","text":"Squad","shortText":"Squad","isExternal":false,"isPremium":false,"isHidden":false}],"record":"7-1-3, 22 pts","records":[],"group":"1","recordStats":{"awayPointsFor":{"value":7.0},"pointsAgainst":{"value":8.0},"awayGamesPlayed":{"value":5.0},"awayWins":{"value":2.0},"losses":{"value":3.0},"points":{"value":22.0},"homeWins":{"value":5.0},"pointDifferential":{"value":15.0},"homePointsAgainst":{"value":4.0},"gamesPlayed":{"value":11.0},"ties":{"value":1.0},"awayLosses":{"value":2.0},"rank":{"value":2.0},"homePointsFor":{"value":16.0},"awayTies":{"value":1.0},"wins":{"value":7.0},"homeTies":{"value":0.0},"pointsFor":{"value":23.0},"homeLosses":{"value":1.0},"streak":{"value":0.0},"homeGamesPlayed":{"value":6.0},"awayPointsAgainst":{"value":4.0}},"logo":"https://a.espncdn.com/i/teamlogos/soccer/500/382.png","logoDark":"https://a.espncdn.com/i/teamlogos/soccer/500-dark/382.png","goalieSummary":[{"displayValue":"0 GA, 2 SV","athlete":{"id":"217092","displayName":"Gianluigi Donnarumma","shortName":"G Donnarumma","fullName":"Gianluigi Donnarumma","lastName":"Donnarumma","jersey":"25","team":{"id":"382"},"position":"G"}}]}],"neutralSite":false,"conferenceCompetition":false,"onDisneyNetwork":false,"appLinks":[{"rel":["summary","sportscenter","app","event"],"href":"sportscenter://x-callback-url/showGame?sportName=soccer&leagueAbbrev=eng.1&gameId=740702","text":"Summary","shortText":"Summary"}]}]}]}]}